setup.py
bombbomb/__init__.py
bombbomb/api_client.py
bombbomb/configuration.py
bombbomb/rest.py
bombbomb.egg-info/PKG-INFO
bombbomb.egg-info/SOURCES.txt
bombbomb.egg-info/dependency_links.txt
bombbomb.egg-info/requires.txt
bombbomb.egg-info/top_level.txt
bombbomb/apis/__init__.py
bombbomb/apis/accounts_api.py
bombbomb/apis/automations_api.py
bombbomb/apis/contacts_api.py
bombbomb/apis/curriculum_api.py
bombbomb/apis/emails_api.py
bombbomb/apis/files_api.py
bombbomb/apis/integrations_api.py
bombbomb/apis/lists_api.py
bombbomb/apis/orders_api.py
bombbomb/apis/prompts_api.py
bombbomb/apis/socials_api.py
bombbomb/apis/teams_api.py
bombbomb/apis/utilities_api.py
bombbomb/apis/videos_api.py
bombbomb/apis/webhooks_api.py
bombbomb/models/__init__.py
bombbomb/models/bb_web_hook.py
bombbomb/models/curriculum.py
bombbomb/models/curriculum_user_progress.py
bombbomb/models/curriculum_with_progress.py
bombbomb/models/hosted_doc.py
bombbomb/models/inline_response_200.py
bombbomb/models/inline_response_200_items.py
bombbomb/models/jericho_configuration.py
bombbomb/models/jericho_performance.py
bombbomb/models/o_auth_client.py
bombbomb/models/prompt_bot.py
bombbomb/models/prompt_bot_bot.py
bombbomb/models/sign_upload_request.py
bombbomb/models/sign_upload_response.py
bombbomb/models/string.py
bombbomb/models/team_public_representation.py
bombbomb/models/video_email_prompt.py
bombbomb/models/video_encoding_status_response.py
bombbomb/models/video_public_representation.py
bombbomb/models/video_recorder_method_response.py
test/__init__.py
test/test_accounts_api.py
test/test_automations_api.py
test/test_bb_web_hook.py
test/test_contacts_api.py
test/test_curriculum.py
test/test_curriculum_api.py
test/test_curriculum_user_progress.py
test/test_curriculum_with_progress.py
test/test_emails_api.py
test/test_files_api.py
test/test_hosted_doc.py
test/test_inline_response_200.py
test/test_inline_response_200_items.py
test/test_integrations_api.py
test/test_jericho_configuration.py
test/test_jericho_performance.py
test/test_lists_api.py
test/test_o_auth_client.py
test/test_orders_api.py
test/test_prompt_bot.py
test/test_prompt_bot_bot.py
