Metadata-Version: 1.0
Name: bombbomb
Version: 2.0.25797
Summary: BombBomb
Home-page: UNKNOWN
Author: UNKNOWN
Author-email: UNKNOWN
License: UNKNOWN
Keywords: Swagger,BombBomb
Platform: UNKNOWN
